coral/__init__.py
coral/__main__.py
coral/accuracy.py
coral/basecall.py
coral/caller.py
coral/dataset.py
coral/decoder.py
coral/download.py
coral/encoder.py
coral/main.py
coral/model.py
coral/train.py
coral/util.py
coral/version.py
coral/configs/basecall_config.json
coral_call-2.1.dist-info/LICENSE
coral_call-2.1.dist-info/METADATA
coral_call-2.1.dist-info/WHEEL
coral_call-2.1.dist-info/entry_points.txt
coral_call-2.1.dist-info/top_level.txt
coral_call-2.1.dist-info/RECORD
