Metadata-Version: 2.2
Name: coral-call
Version: 2.1
Summary: A dual context-aware basecaller for nanopore direct RNA sequencing
Author: ShaoHui Xie
Author-email: 2060271006@email.szu.edu.cn
Classifier: Programming Language :: Python :: 3 :: Only
Classifier: Operating System :: Unix
Classifier: Topic :: Scientific/Engineering :: Bio-Informatics
Requires-Python: >=3.10
License-File: LICENSE
Requires-Dist: numpy==1.26.4
Requires-Dist: matplotlib==3.10.0
Requires-Dist: seaborn==0.13.2
Requires-Dist: pandas==2.2.3
Requires-Dist: scipy==1.15.1
Requires-Dist: ont-fast5-api==4.1.3
Requires-Dist: biopython==1.85
Requires-Dist: parasail==1.3.4
Requires-Dist: tqdm>=4.64.1
Requires-Dist: pysam==0.22.1
Requires-Dist: h5py==3.12.1
Requires-Dist: tensorboard==2.18.0
Requires-Dist: tensorboard-data-server==0.7.2
Requires-Dist: tensorboardX==2.6.2.2
Requires-Dist: pod5==0.3.23
Requires-Dist: lib-pod5==0.3.23
Requires-Dist: requests==2.32.5
Requires-Dist: packaging==24.2
Requires-Dist: ninja==1.11.1.3
Requires-Dist: psutil==6.1.1
Requires-Dist: einops==0.8.0
Requires-Dist: tabulate==0.9.0
Dynamic: author
Dynamic: author-email
Dynamic: classifier
Dynamic: requires-dist
Dynamic: requires-python
Dynamic: summary
